{
	"Class": [
		{
			"Name": "Анастасія",
			"Evaluations": "Відмінник"
		},
		{
			"Name": "Джек",
			"Evaluations": "Хорошист"
		},
		{
			"Name": "Ксенія",
			"Evaluations": "Хорошист"
		},
		{
			"Name": "Сергій",
			"Evaluations": "Двієчник"
		},
		{
			"Name": "Абдула",
			"Evaluations": "Хорошист"
		},
		{
			"Name": "Ахмед",
			"Evaluations": "Двієчник"
		},
				{
			"Name": "Євгеній",
			"Evaluations": "Відмінник"
		},
		{
			"Name": "Джон",
			"Evaluations": "Хорошист"
		},
		{
			"Name": "Ксандр",
			"Evaluations": "Хорошист"
		},
		{
			"Name": "Андрій",
			"Evaluations": "Двієчник"
		},
		{
			"Name": "Аліна",
			"Evaluations": "Хорошист"
		},
		{
			"Name": "Астрід",
			"Evaluations": "Двієчник"
		},
		{
			"Name": "Ліза",
			"Evaluations": "Хорошист"
		}
	]
}